LICENSE
README.md
setup.py
mlabican/__init__.py
mlabican/selfTrainingInitial.py
mlabican.egg-info/PKG-INFO
mlabican.egg-info/SOURCES.txt
mlabican.egg-info/dependency_links.txt
mlabican.egg-info/requires.txt
mlabican.egg-info/top_level.txt